openbb_technical/__init__.py
openbb_technical/helpers.py
openbb_technical/py.typed
openbb_technical/relative_rotation.py
openbb_technical/technical_router.py
openbb_technical/technical_views.py
openbb_technical-1.5.1.dist-info/METADATA
openbb_technical-1.5.1.dist-info/WHEEL
openbb_technical-1.5.1.dist-info/entry_points.txt
openbb_technical-1.5.1.dist-info/RECORD
